[{"Name":"Samsung Galaxy S23\u002B 256 GB Pink Light","Price":14999,"Link":"https://darwin.md/samsung-galaxy-s23-8-gb-256-gb-light-pink.html","Resolution":"2340x1080"},{"Name":"Ulefone Armor 13 256 GB Silver Black","Price":4999,"Link":"https://darwin.md/ulefone-armor-13-8-gb-256-gb-black.html","Resolution":"Resolution not found"},{"Name":"Samsung Galaxy A34 128 GB Black","Price":4599,"Link":"https://darwin.md/samsung-galaxy-a34-6-gb-128-gb-black.html","Resolution":"2340x1080"},{"Name":"Samsung Galaxy A34 256 GB Silver","Price":4999,"Link":"https://darwin.md/samsung-galaxy-a34-8-gb-256-gb-silver.html","Resolution":"2340x1080"},{"Name":"Samsung Galaxy A54 128 GB Black","Price":5999,"Link":"https://darwin.md/samsung-galaxy-a54-6-gb-128-gb-black.html","Resolution":"2400x1080"},{"Name":"Samsung Galaxy M34 128 GB Silver","Price":4199,"Link":"https://darwin.md/samsung-galaxy-m34-m346-8-gb-128-gb-dual-sim-5g-silver.html","Resolution":"2340x1080"},{"Name":"Samsung Galaxy A34 256 GB Black","Price":4999,"Link":"https://darwin.md/samsung-galaxy-a34-8-gb-256-gb-black.html","Resolution":"2340x1080"},{"Name":"Samsung Galaxy A34 128 GB Silver","Price":4599,"Link":"https://darwin.md/samsung-galaxy-a34-6-gb-128-gb-silver.html","Resolution":"2340x1080"},{"Name":"Samsung Galaxy A54 256 GB Violet","Price":6999,"Link":"https://darwin.md/samsung-galaxy-a54-8-gb-256-gb-violet.html","Resolution":"2400x1080"},{"Name":"Samsung Galaxy A34 256 GB Violet Light","Price":4999,"Link":"https://darwin.md/samsung-galaxy-a34-8-gb-256-gb-light-violet.html","Resolution":"2340x1080"},{"Name":"Samsung Galaxy A54 256 GB Green","Price":6999,"Link":"https://darwin.md/samsung-galaxy-a54-8-gb-256-gb-green.html","Resolution":"2400x1080"},{"Name":"Realme C35 128 GB Black","Price":2199,"Link":"https://darwin.md/realme-c35-4-gb-128-gb-black.html","Resolution":"2408x1080"},{"Name":"Samsung Galaxy A54 256 GB Beige","Price":6999,"Link":"https://darwin.md/samsung-galaxy-a54-8-gb-256-gb-beige.html","Resolution":"2400x1080"},{"Name":"Samsung Galaxy Flip4 128 GB Graphite","Price":9999,"Link":"https://darwin.md/samsung-galaxy-flip4-f721-8-gb-128-gb-single-sim-5g-graphite.html","Resolution":"2640x1080"},{"Name":"Samsung Galaxy A34 128 GB Violet Light","Price":4599,"Link":"https://darwin.md/samsung-galaxy-a34-6-gb-128-gb-light-violet.html","Resolution":"2340x1080"},{"Name":"Samsung Galaxy M34 128 GB Dark Blue","Price":4199,"Link":"https://darwin.md/samsung-galaxy-m34-m346-6-gb-128-gb-dual-sim-5gdark-blue.html","Resolution":"2340x1080"},{"Name":"Samsung Galaxy A54 128 GB Beige","Price":5999,"Link":"https://darwin.md/samsung-galaxy-a54-6-gb-128-gb-beige.html","Resolution":"2400x1080"},{"Name":"Samsung Galaxy A34 256 GB Green Light","Price":4999,"Link":"https://darwin.md/samsung-galaxy-a34-8-gb-256-gb-light-green.html","Resolution":"2340x1080"},{"Name":"Samsung Galaxy M34 128 GB Blue","Price":4199,"Link":"https://darwin.md/samsung-galaxy-m34-m346-6-gb-128-gb-dual-sim-5g-blue.html","Resolution":"2340x1080"},{"Name":"Samsung Galaxy A54 128 GB Violet","Price":5999,"Link":"https://darwin.md/samsung-galaxy-a54-6-gb-128-gb-violet.html","Resolution":"2400x1080"}]